Workbook

Sheet Dashboard
A1: Engineering Project Roadmap — Executive Dashboard
A3: Beginner → Intermediate → Industry-Level → Research-Level | Electronics, Embedded Systems, VLSI, AI/ML, Edge AI & Telecommunications
A5: Total Projects | C5: Easy Projects | E5: Intermediate Projects | G5: Industry Projects | I5: Faculty Projects | K5: Research Internship Projects
A6: =SUM(G16:G20) -> 180 | C6: =COUNTA('Easy Projects'!$A$3:$A$1000) -> 50 | E6: =COUNTA('Intermediate Projects'!$A$3:$A$1000) -> 50 | G6: =COUNTA('Industry Projects'!$A$3:$A$1000) -> 36 | I6: =COUNTA('Faculty Projects'!$A$3:$A$1000) -> 22 | K6: =COUNTA('Research Internship Projects'!$A$3:$A$1000) -> 22
F14: Projects by Difficulty Level | I14: Projects by Domain
F15: Difficulty Level | G15: Project Count | I15: Domain | J15: Project Count
F16: Easy | G16: =COUNTA('Easy Projects'!$A$3:$A$1000) -> 50 | I16: Management Systems | J16: =COUNTIF('Easy Projects'!$B:$B,$I16)+COUNTIF('Intermediate Projects'!$B:$B,$I16)+COUNTIF('Industry Projects'!$B:$B,$I16)+COUNTIF('Faculty Projects'!$B:$B,$I16)+COUNTIF('Research Internship Projects'!$B:$B,$I16) -> 24
F17: Intermediate | G17: =COUNTA('Intermediate Projects'!$A$3:$A$1000) -> 50 | I17: Embedded Systems | J17: =COUNTIF('Easy Projects'!$B:$B,$I17)+COUNTIF('Intermediate Projects'!$B:$B,$I17)+COUNTIF('Industry Projects'!$B:$B,$I17)+COUNTIF('Faculty Projects'!$B:$B,$I17)+COUNTIF('Research Internship Projects'!$B:$B,$I17) -> 34
F18: Industry | G18: =COUNTA('Industry Projects'!$A$3:$A$1000) -> 36 | I18: VLSI | J18: =COUNTIF('Easy Projects'!$B:$B,$I18)+COUNTIF('Intermediate Projects'!$B:$B,$I18)+COUNTIF('Industry Projects'!$B:$B,$I18)+COUNTIF('Faculty Projects'!$B:$B,$I18)+COUNTIF('Research Internship Projects'!$B:$B,$I18) -> 29
F19: Faculty | G19: =COUNTA('Faculty Projects'!$A$3:$A$1000) -> 22 | I19: AI/ML | J19: =COUNTIF('Easy Projects'!$B:$B,$I19)+COUNTIF('Intermediate Projects'!$B:$B,$I19)+COUNTIF('Industry Projects'!$B:$B,$I19)+COUNTIF('Faculty Projects'!$B:$B,$I19)+COUNTIF('Research Internship Projects'!$B:$B,$I19) -> 34
F20: Research | G20: =COUNTA('Research Internship Projects'!$A$3:$A$1000) -> 22 | I20: Edge AI | J20: =COUNTIF('Easy Projects'!$B:$B,$I20)+COUNTIF('Intermediate Projects'!$B:$B,$I20)+COUNTIF('Industry Projects'!$B:$B,$I20)+COUNTIF('Faculty Projects'!$B:$B,$I20)+COUNTIF('Research Internship Projects'!$B:$B,$I20) -> 28
I21: Telecommunications | J21: =COUNTIF('Easy Projects'!$B:$B,$I21)+COUNTIF('Intermediate Projects'!$B:$B,$I21)+COUNTIF('Industry Projects'!$B:$B,$I21)+COUNTIF('Faculty Projects'!$B:$B,$I21)+COUNTIF('Research Internship Projects'!$B:$B,$I21) -> 31
A24: Domain × Difficulty Matrix
A25: Domain | B25: Easy | C25: Intermediate | D25: Industry | E25: Faculty | F25: Research
A26: Management Systems | B26: =COUNTIF('Easy Projects'!$B:$B,$A26) -> 8 | C26: =COUNTIF('Intermediate Projects'!$B:$B,$A26) -> 8 | D26: =COUNTIF('Industry Projects'!$B:$B,$A26) -> 6 | E26: =COUNTIF('Faculty Projects'!$B:$B,$A26) -> 2 | F26: =COUNTIF('Research Internship Projects'!$B:$B,$A26) -> 0
A27: Embedded Systems | B27: =COUNTIF('Easy Projects'!$B:$B,$A27) -> 9 | C27: =COUNTIF('Intermediate Projects'!$B:$B,$A27) -> 9 | D27: =COUNTIF('Industry Projects'!$B:$B,$A27) -> 6 | E27: =COUNTIF('Faculty Projects'!$B:$B,$A27) -> 7 | F27: =COUNTIF('Research Internship Projects'!$B:$B,$A27) -> 3
A28: VLSI | B28: =COUNTIF('Easy Projects'!$B:$B,$A28) -> 8 | C28: =COUNTIF('Intermediate Projects'!$B:$B,$A28) -> 8 | D28: =COUNTIF('Industry Projects'!$B:$B,$A28) -> 6 | E28: =COUNTIF('Faculty Projects'!$B:$B,$A28) -> 2 | F28: =COUNTIF('Research Internship Projects'!$B:$B,$A28) -> 5
A29: AI/ML | B29: =COUNTIF('Easy Projects'!$B:$B,$A29) -> 9 | C29: =COUNTIF('Intermediate Projects'!$B:$B,$A29) -> 9 | D29: =COUNTIF('Industry Projects'!$B:$B,$A29) -> 6 | E29: =COUNTIF('Faculty Projects'!$B:$B,$A29) -> 5 | F29: =COUNTIF('Research Internship Projects'!$B:$B,$A29) -> 5
A30: Edge AI | B30: =COUNTIF('Easy Projects'!$B:$B,$A30) -> 8 | C30: =COUNTIF('Intermediate Projects'!$B:$B,$A30) -> 8 | D30: =COUNTIF('Industry Projects'!$B:$B,$A30) -> 6 | E30: =COUNTIF('Faculty Projects'!$B:$B,$A30) -> 3 | F30: =COUNTIF('Research Internship Projects'!$B:$B,$A30) -> 3
A31: Telecommunications | B31: =COUNTIF('Easy Projects'!$B:$B,$A31) -> 8 | C31: =COUNTIF('Intermediate Projects'!$B:$B,$A31) -> 8 | D31: =COUNTIF('Industry Projects'!$B:$B,$A31) -> 6 | E31: =COUNTIF('Faculty Projects'!$B:$B,$A31) -> 3 | F31: =COUNTIF('Research Internship Projects'!$B:$B,$A31) -> 6

Sheet Easy Projects
A1: Easy Projects — Engineering Project Roadmap
A2: Project ID | B2: Domain | C2: Project Name | D2: Difficulty Level | E2: Project Type | F2: Brief Description | G2: Key Concepts Learned | H2: Technologies Used | I2: Hardware Required | J2: Software Required | K2: Estimated Duration | L2: Team Size | M2: Resume Impact | N2: Placement Relevance | O2: Research Potential | P2: Startup Potential | Q2: Suitable Year | R2: Difficulty Score (1-10)
A3: P001 | B3: Management Systems | C3: Student Attendance System | D3: Easy | E3: Mini Project | F3: A beginner-friendly web-based application that lets users record and track daily student attendance through a structured, database-backed system. | G3: CRUD operations, basic database design, client-server model, form handling & validation | H3: HTML, CSS, JavaScript, Python (Flask) / PHP, SQLite | I3: None (software-only project) | J3: VS Code, XAMPP / Flask dev server, SQLite Browser, Git | K3: 2-3 weeks | L3: 1 (Individual) | M3: Low | N3: Medium | O3: Low | P3: Low | Q3: 1st Year | R3: 2
A4: P002 | B4: Management Systems | C4: Library Management System | D4: Easy | E4: Mini Project | F4: A beginner-friendly web-based application that lets users manage book issue, return, and catalog records through a structured, database-backed system. | G4: CRUD operations, basic database design, client-server model, form handling & validation | H4: HTML, CSS, JavaScript, Python (Flask) / PHP, SQLite | I4: None (software-only project) | J4: VS Code, XAMPP / Flask dev server, SQLite Browser, Git | K4: 2-3 weeks | L4: 1 (Individual) | M4: Low | N4: Medium | O4: Low | P4: Low | Q4: 1st Year | R4: 3
A5: P003 | B5: Management Systems | C5: Simple Inventory Tracker | D5: Easy | E5: Mini Project | F5: A beginner-friendly web-based application that lets users track stock levels and item entries for a small store through a structured, database-backed system. | G5: CRUD operations, basic database design, client-server model, form handling & validation | H5: HTML, CSS, JavaScript, Python (Flask) / PHP, SQLite | I5: None (software-only project) | J5: VS Code, XAMPP / Flask dev server, SQLite Browser, Git | K5: 2-3 weeks | L5: 1 (Individual) | M5: Low | N5: Medium | O5: Low | P5: Low | Q5: 1st Year | R5: 1
A6: P004 | B6: Management Systems | C6: Event Registration Portal | D6: Easy | E6: Mini Project | F6: A beginner-friendly web-based application that lets users let participants register and view event details online through a structured, database-backed system. | G6: CRUD operations, basic database design, client-server model, form handling & validation | H6: HTML, CSS, JavaScript, Python (Flask) / PHP, SQLite | I6: None (software-only project) | J6: VS Code, XAMPP / Flask dev server, SQLite Browser, Git | K6: 2-3 weeks | L6: 1 (Individual) | M6: Low | N6: Medium | O6: Low | P6: Low | Q6: 1st Year | R6: 2
A7: P005 | B7: Management Systems | C7: Simple Billing & Invoicing System | D7: Easy | E7: Mini Project | F7: A beginner-friendly web-based application that lets users generate and store customer bills and invoices through a structured, database-backed system. | G7: CRUD operations, basic database design, client-server model, form handling & validation | H7: HTML, CSS, JavaScript, Python (Flask) / PHP, SQLite | I7: None (software-only project) | J7: VS Code, XAMPP / Flask dev server, SQLite Browser, Git | K7: 2-3 weeks | L7: 1 (Individual) | M7: Low | N7: Medium | O7: Low | P7: Low | Q7: 1st Year | R7: 3
A8: P006 | B8: Management Systems | C8: Student Result Management System | D8: Easy | E8: Mini Project | F8: A beginner-friendly web-based application that lets users record, calculate, and display student marks and grades through a structured, database-backed system. | G8: CRUD operations, basic database design, client-server model, form handling & validation | H8: HTML, CSS, JavaScript, Python (Flask) / PHP, SQLite | I8: None (software-only project) | J8: VS Code, XAMPP / Flask dev server, SQLite Browser, Git | K8: 2-3 weeks | L8: 1 (Individual) | M8: Low | N8: Medium | O8: Low | P8: Low | Q8: 1st Year | R8: 1
A9: P007 | B9: Management Systems | C9: Digital Contact Book Application | D9: Easy | E9: Mini Project | F9: A beginner-friendly web-based application that lets users store, search, and manage personal contacts through a structured, database-backed system. | G9: CRUD operations, basic database design, client-server model, form handling & validation | H9: HTML, CSS, JavaScript, Python (Flask) / PHP, SQLite | I9: None (software-only project) | J9: VS Code, XAMPP / Flask dev server, SQLite Browser, Git | K9: 2-3 weeks | L9: 1 (Individual) | M9: Low | N9: Medium | O9: Low | P9: Low | Q9: 1st Year | R9: 2
A10: P008 | B10: Management Systems | C10: Online Quiz Application | D10: Easy | E10: Mini Project | F10: A beginner-friendly web-based application that lets users conduct timed quizzes and auto-score student responses through a structured, database-backed system. | G10: CRUD operations, basic database design, client-server model, form handling & validation | H10: HTML, CSS, JavaScript, Python (Flask) / PHP, SQLite | I10: None (software-only project) | J10: VS Code, XAMPP / Flask dev server, SQLite Browser, Git | K10: 2-3 weeks | L10: 1 (Individual) | M10: Low | N10: Medium | O10: Low | P10: Low | Q10: 1st Year | R10: 3
A11: P009 | B11: Embedded Systems | C11: Temperature Monitoring System (ESP32) | D11: Easy | E11: Mini Project | F11: A beginner-friendly hardware-software project that uses microcontrollers and sensors to sense ambient temperature and display live readings. | G11: digital I/O & interrupts, sensor interfacing, basic circuit design, microcontroller programming fundamentals | H11: Arduino / ESP32, Embedded C/C++ | I11: Arduino Uno / ESP32 board, breadboard, jumper wires, basic sensors (LDR, DHT11, ultrasonic, IR) | J11: Arduino IDE | K11: 2-3 weeks | L11: 1 (Individual) | M11: Low | N11: Medium | O11: Low | P11: Low | Q11: 1st Year | R11: 1
A12: P010 | B12: Embedded Systems | C12: Smart Dustbin | D12: Easy | E12: Mini Project | F12: A beginner-friendly hardware-software project that uses microcontrollers and sensors to automatically open a dustbin lid using an ultrasonic sensor. | G12: digital I/O & interrupts, sensor interfacing, basic circuit design, microcontroller programming fundamentals | H12: Arduino / ESP32, Embedded C/C++ | I12: Arduino Uno / ESP32 board, breadboard, jumper wires, basic sensors (LDR, DHT11, ultrasonic, IR) | J12: Arduino IDE | K12: 2-3 weeks | L12: 1 (Individual) | M12: Low | N12: Medium | O12: Low | P12: Low | Q12: 1st Year | R12: 2
A13: P011 | B13: Embedded Systems | C13: Smart Street Light | D13: Easy | E13: Mini Project | F13: A beginner-friendly hardware-software project that uses microcontrollers and sensors to switch street lights on/off automatically based on ambient light. | G13: digital I/O & interrupts, sensor interfacing, basic circuit design, microcontroller programming fundamentals | H13: Arduino / ESP32, Embedded C/C++ | I13: Arduino Uno / ESP32 board, breadboard, jumper wires, basic sensors (LDR, DHT11, ultrasonic, IR) | J13: Arduino IDE | K13: 2-3 weeks | L13: 1 (Individual) | M13: Low | N13: Medium | O13: Low | P13: Low | Q13: 1st Year | R13: 3
A14: P012 | B14: Embedded Systems | C14: Water Level Indicator | D14: Easy | E14: Mini Project | F14: A beginner-friendly hardware-software project that uses microcontrollers and sensors to detect and alert on water tank levels using sensors. | G14: digital I/O & interrupts, sensor interfacing, basic circuit design, microcontroller programming fundamentals | H14: Arduino / ESP32, Embedded C/C++ | I14: Arduino Uno / ESP32 board, breadboard, jumper wires, basic sensors (LDR, DHT11, ultrasonic, IR) | J14: Arduino IDE | K14: 2-3 weeks | L14: 1 (Individual) | M14: Low | N14: Medium | O14: Low | P14: Low | Q14: 1st Year | R14: 1
... A52: P050 | B52: Telecommunications | C52: DTMF-based Device Control | D52: Easy | E52: Mini Project | F52: A beginner-friendly communication-systems project that controlling appliances remotely using phone DTMF tones. | G52: serial communication, AT command sets, basic RF principles, wireless signal fundamentals | H52: GSM module (SIM800L), Arduino, Bluetooth (HC-05) | I52: Arduino Uno, GSM/Bluetooth/RF module, antenna | J52: Arduino IDE | K52: 2-3 weeks | L52: 1 (Individual) | M52: Low | N52: Medium | O52: Low | P52: Low | Q52: 1st Year | R52: 3

Sheet Intermediate Projects
A1: Intermediate Projects — Engineering Project Roadmap
A2: Project ID | B2: Domain | C2: Project Name | D2: Difficulty Level | E2: Project Type | F2: Brief Description | G2: Key Concepts Learned | H2: Technologies Used | I2: Hardware Required | J2: Software Required | K2: Estimated Duration | L2: Team Size | M2: Resume Impact | N2: Placement Relevance | O2: Research Potential | P2: Startup Potential | Q2: Suitable Year | R2: Difficulty Score (1-10)
A3: P051 | B3: Management Systems | C3: College ERP System (Core Modules) | D3: Intermediate | E3: Mini/Major Project | F3: A moderately complex web-based application that lets users manage admissions, academics, and fee records for a college through a structured, database-backed system. | G3: RESTful API design, authentication & authorization, relational database normalization, MVC architecture | H3: React.js / Angular, Node.js / Django, MySQL / PostgreSQL, REST APIs | I3: None (software-only project) | J3: VS Code, Postman, MySQL Workbench, Git/GitHub | K3: 4-8 weeks | L3: 2-3 | M3: Medium | N3: High | O3: Low-Medium | P3: Medium | Q3: 2nd - Early 3rd Year | R3: 4
A4: P052 | B4: Management Systems | C4: Hospital Management System | D4: Intermediate | E4: Mini/Major Project | F4: A moderately complex web-based application that lets users manage patient records, appointments, and billing for a clinic through a structured, database-backed system. | G4: RESTful API design, authentication & authorization, relational database normalization, MVC architecture | H4: React.js / Angular, Node.js / Django, MySQL / PostgreSQL, REST APIs | I4: None (software-only project) | J4: VS Code, Postman, MySQL Workbench, Git/GitHub | K4: 4-8 weeks | L4: 2-3 | M4: Medium | N4: High | O4: Low-Medium | P4: Medium | Q4: 2nd - Early 3rd Year | R4: 5
A5: P053 | B5: Management Systems | C5: Multi-Branch Inventory Management System | D5: Intermediate | E5: Mini/Major Project | F5: A moderately complex web-based application that lets users track stock across multiple store branches with sync through a structured, database-backed system. | G5: RESTful API design, authentication & authorization, relational database normalization, MVC architecture | H5: React.js / Angular, Node.js / Django, MySQL / PostgreSQL, REST APIs | I5: None (software-only project) | J5: VS Code, Postman, MySQL Workbench, Git/GitHub | K5: 4-8 weeks | L5: 2-3 | M5: Medium | N5: High | O5: Low-Medium | P5: Medium | Q5: 2nd - Early 3rd Year | R5: 6
A6: P054 | B6: Management Systems | C6: Recruitment Management System | D6: Intermediate | E6: Mini/Major Project | F6: A moderately complex web-based application that lets users manage job postings, applications, and shortlisting workflows through a structured, database-backed system. | G6: RESTful API design, authentication & authorization, relational database normalization, MVC architecture | H6: React.js / Angular, Node.js / Django, MySQL / PostgreSQL, REST APIs | I6: None (software-only project) | J6: VS Code, Postman, MySQL Workbench, Git/GitHub | K6: 4-8 weeks | L6: 2-3 | M6: Medium | N6: High | O6: Low-Medium | P6: Medium | Q6: 2nd - Early 3rd Year | R6: 4
A7: P055 | B7: Management Systems | C7: Online Learning Management System | D7: Intermediate | E7: Mini/Major Project | F7: A moderately complex web-based application that lets users deliver courses, assignments, and grading to students online through a structured, database-backed system. | G7: RESTful API design, authentication & authorization, relational database normalization, MVC architecture | H7: React.js / Angular, Node.js / Django, MySQL / PostgreSQL, REST APIs | I7: None (software-only project) | J7: VS Code, Postman, MySQL Workbench, Git/GitHub | K7: 4-8 weeks | L7: 2-3 | M7: Medium | N7: High | O7: Low-Medium | P7: Medium | Q7: 2nd - Early 3rd Year | R7: 5
A8: P056 | B8: Management Systems | C8: Restaurant Table Booking & Ordering System | D8: Intermediate | E8: Mini/Major Project | F8: A moderately complex web-based application that lets users handle table reservations and online food ordering through a structured, database-backed system. | G8: RESTful API design, authentication & authorization, relational database normalization, MVC architecture | H8: React.js / Angular, Node.js / Django, MySQL / PostgreSQL, REST APIs | I8: None (software-only project) | J8: VS Code, Postman, MySQL Workbench, Git/GitHub | K8: 4-8 weeks | L8: 2-3 | M8: Medium | N8: High | O8: Low-Medium | P8: Medium | Q8: 2nd - Early 3rd Year | R8: 6
A9: P057 | B9: Management Systems | C9: Employee Payroll Management System | D9: Intermediate | E9: Mini/Major Project | F9: A moderately complex web-based application that lets users automate salary computation, deductions, and payslips through a structured, database-backed system. | G9: RESTful API design, authentication & authorization, relational database normalization, MVC architecture | H9: React.js / Angular, Node.js / Django, MySQL / PostgreSQL, REST APIs | I9: None (software-only project) | J9: VS Code, Postman, MySQL Workbench, Git/GitHub | K9: 4-8 weeks | L9: 2-3 | M9: Medium | N9: High | O9: Low-Medium | P9: Medium | Q9: 2nd - Early 3rd Year | R9: 4
A10: P058 | B10: Management Systems | C10: Real Estate Listing Portal | D10: Intermediate | E10: Mini/Major Project | F10: A moderately complex web-based application that lets users let users browse, filter, and enquire about property listings through a structured, database-backed system. | G10: RESTful API design, authentication & authorization, relational database normalization, MVC architecture | H10: React.js / Angular, Node.js / Django, MySQL / PostgreSQL, REST APIs | I10: None (software-only project) | J10: VS Code, Postman, MySQL Workbench, Git/GitHub | K10: 4-8 weeks | L10: 2-3 | M10: Medium | N10: High | O10: Low-Medium | P10: Medium | Q10: 2nd - Early 3rd Year | R10: 5
A11: P059 | B11: Embedded Systems | C11: Smart Home Automation System | D11: Intermediate | E11: Mini/Major Project | F11: A moderately complex hardware-software project that uses microcontrollers and sensors to control home appliances remotely over Wi-Fi/app. | G11: IoT communication protocols, cloud data integration, wireless connectivity (Wi-Fi/BLE), real-time data logging & alerts | H11: ESP32 / ESP8266, MQTT, Firebase / Blynk, C/C++, Python | I11: ESP32/ESP8266 board, GPS module, relays, motor drivers, assorted sensors, LCD/OLED display | J11: Arduino IDE, VS Code + PlatformIO, Blynk/Firebase console | K11: 4-8 weeks | L11: 2-3 | M11: Medium | N11: High | O11: Low-Medium | P11: Medium | Q11: 2nd - Early 3rd Year | R11: 6
A12: P060 | B12: Embedded Systems | C12: GPS Vehicle Tracking System | D12: Intermediate | E12: Mini/Major Project | F12: A moderately complex hardware-software project that uses microcontrollers and sensors to track and log a vehicle's live location over a map. | G12: IoT communication protocols, cloud data integration, wireless connectivity (Wi-Fi/BLE), real-time data logging & alerts | H12: ESP32 / ESP8266, MQTT, Firebase / Blynk, C/C++, Python | I12: ESP32/ESP8266 board, GPS module, relays, motor drivers, assorted sensors, LCD/OLED display | J12: Arduino IDE, VS Code + PlatformIO, Blynk/Firebase console | K12: 4-8 weeks | L12: 2-3 | M12: Medium | N12: High | O12: Low-Medium | P12: Medium | Q12: 2nd - Early 3rd Year | R12: 4
A13: P061 | B13: Embedded Systems | C13: Smart Energy Meter | D13: Intermediate | E13: Mini/Major Project | F13: A moderately complex hardware-software project that uses microcontrollers and sensors to measure and report household power consumption in real time. | G13: IoT communication protocols, cloud data integration, wireless connectivity (Wi-Fi/BLE), real-time data logging & alerts | H13: ESP32 / ESP8266, MQTT, Firebase / Blynk, C/C++, Python | I13: ESP32/ESP8266 board, GPS module, relays, motor drivers, assorted sensors, LCD/OLED display | J13: Arduino IDE, VS Code + PlatformIO, Blynk/Firebase console | K13: 4-8 weeks | L13: 2-3 | M13: Medium | N13: High | O13: Low-Medium | P13: Medium | Q13: 2nd - Early 3rd Year | R13: 5
A14: P062 | B14: Embedded Systems | C14: Smart Irrigation System | D14: Intermediate | E14: Mini/Major Project | F14: A moderately complex hardware-software project that uses microcontrollers and sensors to automate irrigation based on soil-moisture sensor data. | G14: IoT communication protocols, cloud data integration, wireless connectivity (Wi-Fi/BLE), real-time data logging & alerts | H14: ESP32 / ESP8266, MQTT, Firebase / Blynk, C/C++, Python | I14: ESP32/ESP8266 board, GPS module, relays, motor drivers, assorted sensors, LCD/OLED display | J14: Arduino IDE, VS Code + PlatformIO, Blynk/Firebase console | K14: 4-8 weeks | L14: 2-3 | M14: Medium | N14: High | O14: Low-Medium | P14: Medium | Q14: 2nd - Early 3rd Year | R14: 6
... A52: P100 | B52: Telecommunications | C52: Cognitive Radio Spectrum Sensing | D52: Intermediate | E52: Mini/Major Project | F52: A moderately complex communication-systems project that detecting unused spectrum bands for opportunistic access. | G52: modulation techniques, spectrum analysis, long-range (LPWAN) communication protocols, network traffic analysis | H52: LoRa (SX1278), RTL-SDR, Python, MATLAB | I52: LoRa transceiver modules, RTL-SDR dongle, antennas | J52: GNU Radio, MATLAB, Arduino IDE | K52: 4-8 weeks | L52: 2-3 | M52: Medium | N52: High | O52: Low-Medium | P52: Medium | Q52: 2nd - Early 3rd Year | R52: 5

Sheet Industry Projects
A1: Industry Projects — Engineering Project Roadmap
A2: Project ID | B2: Domain | C2: Project Name | D2: Difficulty Level | E2: Project Type | F2: Brief Description | G2: Key Concepts Learned | H2: Technologies Used | I2: Hardware Required | J2: Software Required | K2: Estimated Duration | L2: Team Size | M2: Resume Impact | N2: Placement Relevance | O2: Research Potential | P2: Startup Potential | Q2: Suitable Year | R2: Difficulty Score (1-10)
A3: P101 | B3: Management Systems | C3: Enterprise ERP with Microservices | D3: Industry | E3: Major/Capstone Project | F3: A industry-grade, production-ready web-based application that lets users run a modular, horizontally scalable enterprise resource-planning suite through a structured, database-backed system. | G3: microservices architecture, horizontal scalability & load balancing, CI/CD pipelines, role-based access control, distributed systems design | H3: React/Next.js, Node.js / Spring Boot microservices, PostgreSQL / MongoDB, Docker, Kubernetes, Redis, Kafka | I3: Cloud compute instances (AWS/Azure/GCP) | J3: Docker, Kubernetes, Jenkins/GitHub Actions (CI-CD), Postman, Git | K3: 3-6 months | L3: 3-5 | M3: High | N3: High | O3: Medium | P3: High | Q3: 3rd - Final Year | R3: 9
A4: P102 | B4: Management Systems | C4: Healthcare Management Platform with RBAC & Audit Logs | D4: Industry | E4: Major/Capstone Project | F4: A industry-grade, production-ready web-based application that lets users manage hospital operations with strict role-based access and compliance logging through a structured, database-backed system. | G4: microservices architecture, horizontal scalability & load balancing, CI/CD pipelines, role-based access control, distributed systems design | H4: React/Next.js, Node.js / Spring Boot microservices, PostgreSQL / MongoDB, Docker, Kubernetes, Redis, Kafka | I4: Cloud compute instances (AWS/Azure/GCP) | J4: Docker, Kubernetes, Jenkins/GitHub Actions (CI-CD), Postman, Git | K4: 3-6 months | L4: 3-5 | M4: High | N4: High | O4: Medium | P4: High | Q4: 3rd - Final Year | R4: 7
A5: P103 | B5: Management Systems | C5: Supply Chain Management System | D5: Industry | E5: Major/Capstone Project | F5: A industry-grade, production-ready web-based application that lets users coordinate procurement, logistics, and warehousing across a supply chain through a structured, database-backed system. | G5: microservices architecture, horizontal scalability & load balancing, CI/CD pipelines, role-based access control, distributed systems design | H5: React/Next.js, Node.js / Spring Boot microservices, PostgreSQL / MongoDB, Docker, Kubernetes, Redis, Kafka | I5: Cloud compute instances (AWS/Azure/GCP) | J5: Docker, Kubernetes, Jenkins/GitHub Actions (CI-CD), Postman, Git | K5: 3-6 months | L5: 3-5 | M5: High | N5: High | O5: Medium | P5: High | Q5: 3rd - Final Year | R5: 8
A6: P104 | B6: Management Systems | C6: ATS (Applicant Tracking System) with AI Screening | D6: Industry | E6: Major/Capstone Project | F6: A industry-grade, production-ready web-based application that lets users automate large-scale recruitment pipelines using AI-assisted screening through a structured, database-backed system. | G6: microservices architecture, horizontal scalability & load balancing, CI/CD pipelines, role-based access control, distributed systems design | H6: React/Next.js, Node.js / Spring Boot microservices, PostgreSQL / MongoDB, Docker, Kubernetes, Redis, Kafka | I6: Cloud compute instances (AWS/Azure/GCP) | J6: Docker, Kubernetes, Jenkins/GitHub Actions (CI-CD), Postman, Git | K6: 3-6 months | L6: 3-5 | M6: High | N6: High | O6: Medium | P6: High | Q6: 3rd - Final Year | R6: 9
A7: P105 | B7: Management Systems | C7: Multi-Tenant SaaS CRM Platform | D7: Industry | E7: Major/Capstone Project | F7: A industry-grade, production-ready web-based application that lets users serve multiple client organizations from a single, isolated SaaS backend through a structured, database-backed system. | G7: microservices architecture, horizontal scalability & load balancing, CI/CD pipelines, role-based access control, distributed systems design | H7: React/Next.js, Node.js / Spring Boot microservices, PostgreSQL / MongoDB, Docker, Kubernetes, Redis, Kafka | I7: Cloud compute instances (AWS/Azure/GCP) | J7: Docker, Kubernetes, Jenkins/GitHub Actions (CI-CD), Postman, Git | K7: 3-6 months | L7: 3-5 | M7: High | N7: High | O7: Medium | P7: High | Q7: 3rd - Final Year | R7: 7
A8: P106 | B8: Management Systems | C8: Cloud-based HRMS with Payroll Automation | D8: Industry | E8: Major/Capstone Project | F8: A industry-grade, production-ready web-based application that lets users run enterprise HR operations with automated, compliant payroll processing through a structured, database-backed system. | G8: microservices architecture, horizontal scalability & load balancing, CI/CD pipelines, role-based access control, distributed systems design | H8: React/Next.js, Node.js / Spring Boot microservices, PostgreSQL / MongoDB, Docker, Kubernetes, Redis, Kafka | I8: Cloud compute instances (AWS/Azure/GCP) | J8: Docker, Kubernetes, Jenkins/GitHub Actions (CI-CD), Postman, Git | K8: 3-6 months | L8: 3-5 | M8: High | N8: High | O8: Medium | P8: High | Q8: 3rd - Final Year | R8: 8
A9: P107 | B9: Embedded Systems | C9: Industrial IoT Monitoring & Predictive Maintenance System | D9: Industry | E9: Major/Capstone Project | F9: A industry-grade, production-ready hardware-software project that uses microcontrollers and sensors to predict equipment failure from real-time industrial sensor telemetry. | G9: RTOS task scheduling, predictive-maintenance algorithms, industrial protocols (Modbus/SCADA), mesh networking, edge-to-cloud data pipelines | H9: FreeRTOS, ESP32 / STM32, MQTT / CoAP, edge-to-cloud architecture, Python/Node.js backend | I9: STM32/ESP32 dev boards, industrial-grade sensors, PLC/relay modules, actuators, mesh-network nodes | J9: STM32CubeIDE, AWS IoT Core / Azure IoT Hub, Docker, Grafana | K9: 3-6 months | L9: 3-5 | M9: High | N9: High | O9: Medium | P9: High | Q9: 3rd - Final Year | R9: 9
A10: P108 | B10: Embedded Systems | C10: Autonomous Mobile Robot | D10: Industry | E10: Major/Capstone Project | F10: A industry-grade, production-ready hardware-software project that uses microcontrollers and sensors to navigate and map an environment autonomously using sensor fusion. | G10: RTOS task scheduling, predictive-maintenance algorithms, industrial protocols (Modbus/SCADA), mesh networking, edge-to-cloud data pipelines | H10: FreeRTOS, ESP32 / STM32, MQTT / CoAP, edge-to-cloud architecture, Python/Node.js backend | I10: STM32/ESP32 dev boards, industrial-grade sensors, PLC/relay modules, actuators, mesh-network nodes | J10: STM32CubeIDE, AWS IoT Core / Azure IoT Hub, Docker, Grafana | K10: 3-6 months | L10: 3-5 | M10: High | N10: High | O10: Medium | P10: High | Q10: 3rd - Final Year | R10: 7
A11: P109 | B11: Embedded Systems | C11: Industrial PLC-SCADA Integrated Monitoring System | D11: Industry | E11: Major/Capstone Project | F11: A industry-grade, production-ready hardware-software project that uses microcontrollers and sensors to integrate PLC control with a SCADA dashboard for plant monitoring. | G11: RTOS task scheduling, predictive-maintenance algorithms, industrial protocols (Modbus/SCADA), mesh networking, edge-to-cloud data pipelines | H11: FreeRTOS, ESP32 / STM32, MQTT / CoAP, edge-to-cloud architecture, Python/Node.js backend | I11: STM32/ESP32 dev boards, industrial-grade sensors, PLC/relay modules, actuators, mesh-network nodes | J11: STM32CubeIDE, AWS IoT Core / Azure IoT Hub, Docker, Grafana | K11: 3-6 months | L11: 3-5 | M11: High | N11: High | O11: Medium | P11: High | Q11: 3rd - Final Year | R11: 8
A12: P110 | B12: Embedded Systems | C12: Wireless Mesh Sensor Network | D12: Industry | E12: Major/Capstone Project | F12: A industry-grade, production-ready hardware-software project that uses microcontrollers and sensors to relay sensor data reliably across a self-healing mesh network. | G12: RTOS task scheduling, predictive-maintenance algorithms, industrial protocols (Modbus/SCADA), mesh networking, edge-to-cloud data pipelines | H12: FreeRTOS, ESP32 / STM32, MQTT / CoAP, edge-to-cloud architecture, Python/Node.js backend | I12: STM32/ESP32 dev boards, industrial-grade sensors, PLC/relay modules, actuators, mesh-network nodes | J12: STM32CubeIDE, AWS IoT Core / Azure IoT Hub, Docker, Grafana | K12: 3-6 months | L12: 3-5 | M12: High | N12: High | O12: Medium | P12: High | Q12: 3rd - Final Year | R12: 9
A13: P111 | B13: Embedded Systems | C13: Smart Grid Monitoring System | D13: Industry | E13: Major/Capstone Project | F13: A industry-grade, production-ready hardware-software project that uses microcontrollers and sensors to monitor and balance power distribution across a smart grid. | G13: RTOS task scheduling, predictive-maintenance algorithms, industrial protocols (Modbus/SCADA), mesh networking, edge-to-cloud data pipelines | H13: FreeRTOS, ESP32 / STM32, MQTT / CoAP, edge-to-cloud architecture, Python/Node.js backend | I13: STM32/ESP32 dev boards, industrial-grade sensors, PLC/relay modules, actuators, mesh-network nodes | J13: STM32CubeIDE, AWS IoT Core / Azure IoT Hub, Docker, Grafana | K13: 3-6 months | L13: 3-5 | M13: High | N13: High | O13: Medium | P13: High | Q13: 3rd - Final Year | R13: 7
A14: P112 | B14: Embedded Systems | C14: Fleet Management System with Real-time Telemetry | D14: Industry | E14: Major/Capstone Project | F14: A industry-grade, production-ready hardware-software project that uses microcontrollers and sensors to track and optimize a vehicle fleet using live telemetry data. | G14: RTOS task scheduling, predictive-maintenance algorithms, industrial protocols (Modbus/SCADA), mesh networking, edge-to-cloud data pipelines | H14: FreeRTOS, ESP32 / STM32, MQTT / CoAP, edge-to-cloud architecture, Python/Node.js backend | I14: STM32/ESP32 dev boards, industrial-grade sensors, PLC/relay modules, actuators, mesh-network nodes | J14: STM32CubeIDE, AWS IoT Core / Azure IoT Hub, Docker, Grafana | K14: 3-6 months | L14: 3-5 | M14: High | N14: High | O14: Medium | P14: High | Q14: 3rd - Final Year | R14: 8
... A38: P136 | B38: Telecommunications | C38: AI-based RF Spectrum Monitoring System | D38: Industry | E38: Major/Capstone Project | F38: A industry-grade, production-ready communication-systems project that monitor and classify spectrum usage using AI-driven signal analysis. | G38: 5G network architecture, network slicing, large-scale RF engineering, AI-driven network optimization, Open RAN architecture | H38: 5G NR, O-RAN, SDR, Python/C++, AI/ML for network optimization | I38: USRP SDR platforms, 5G testbed equipment, RF front-ends | J38: srsRAN / OpenAirInterface, MATLAB, Python, Kubernetes | K38: 3-6 months | L38: 3-5 | M38: High | N38: High | O38: Medium | P38: High | Q38: 3rd - Final Year | R38: 8

Sheet Faculty Projects
A1: Faculty Projects — Engineering Project Roadmap
A2: Project ID | B2: Domain | C2: Project Name | D2: Difficulty Level | E2: Project Type | F2: Brief Description | G2: Key Concepts Learned | H2: Technologies Used | I2: Hardware Required | J2: Software Required | K2: Estimated Duration | L2: Team Size | M2: Resume Impact | N2: Placement Relevance | O2: Research Potential | P2: Startup Potential | Q2: Suitable Year | R2: Difficulty Score (1-10)
A3: P137 | B3: Management Systems | C3: Smart Campus Platform | D3: Faculty | E3: Faculty-Guided / Department Project | F3: A faculty-guided, department-scale web-based application that lets users unify attendance, energy, security, and academic data for an entire campus through a structured, database-backed system. | G3: research methodology, systems integration, literature review & benchmarking, experimental design, technical documentation & reporting | H3: Domain-specific research stack (Python/MATLAB/Simulink + domain tools), version-controlled codebase | I3: Lab-scale hardware/testbed appropriate to the domain (provided by department) | J3: MATLAB/Simulink, Python (Jupyter), LaTeX for documentation, Git, domain-specific EDA/ML tooling | K3: 6-12 months | L3: 4-6 (faculty-guided) | M3: High | N3: Medium | O3: High | P3: Medium | Q3: 3rd Year - PG | R3: 9
A4: P138 | B4: AI/ML | C4: Research Data Analytics System | D4: Faculty | E4: Faculty-Guided / Department Project | F4: A faculty-guided, department-scale machine-learning project that trains and evaluates models to aggregate and analyze large-scale departmental research datasets. | G4: research methodology, systems integration, literature review & benchmarking, experimental design, technical documentation & reporting | H4: Domain-specific research stack (Python/MATLAB/Simulink + domain tools), version-controlled codebase | I4: Lab-scale hardware/testbed appropriate to the domain (provided by department) | J4: MATLAB/Simulink, Python (Jupyter), LaTeX for documentation, Git, domain-specific EDA/ML tooling | K4: 6-12 months | L4: 4-6 (faculty-guided) | M4: High | N4: Medium | O4: High | P4: Medium | Q4: 3rd Year - PG | R4: 8
A5: P139 | B5: Embedded Systems | C5: Industrial Automation Platform | D5: Faculty | E5: Faculty-Guided / Department Project | F5: A faculty-guided, department-scale hardware-software project that uses microcontrollers and sensors to automate and monitor multi-stage industrial processes end-to-end. | G5: research methodology, systems integration, literature review & benchmarking, experimental design, technical documentation & reporting | H5: Domain-specific research stack (Python/MATLAB/Simulink + domain tools), version-controlled codebase | I5: Lab-scale hardware/testbed appropriate to the domain (provided by department) | J5: MATLAB/Simulink, Python (Jupyter), LaTeX for documentation, Git, domain-specific EDA/ML tooling | K5: 6-12 months | L5: 4-6 (faculty-guided) | M5: High | N5: Medium | O5: High | P5: Medium | Q5: 3rd Year - PG | R5: 9
A6: P140 | B6: AI/ML | C6: Healthcare Analytics Platform | D6: Faculty | E6: Faculty-Guided / Department Project | F6: A faculty-guided, department-scale machine-learning project that trains and evaluates models to analyze patient-outcome data to surface actionable clinical insights. | G6: research methodology, systems integration, literature review & benchmarking, experimental design, technical documentation & reporting | H6: Domain-specific research stack (Python/MATLAB/Simulink + domain tools), version-controlled codebase | I6: Lab-scale hardware/testbed appropriate to the domain (provided by department) | J6: MATLAB/Simulink, Python (Jupyter), LaTeX for documentation, Git, domain-specific EDA/ML tooling | K6: 6-12 months | L6: 4-6 (faculty-guided) | M6: High | N6: Medium | O6: High | P6: Medium | Q6: 3rd Year - PG | R6: 8
A7: P141 | B7: Embedded Systems | C7: Smart Grid Research Platform | D7: Faculty | E7: Faculty-Guided / Department Project | F7: A faculty-guided, department-scale hardware-software project that uses microcontrollers and sensors to study demand-response and fault behaviour on a lab-scale smart grid. | G7: research methodology, systems integration, literature review & benchmarking, experimental design, technical documentation & reporting | H7: Domain-specific research stack (Python/MATLAB/Simulink + domain tools), version-controlled codebase | I7: Lab-scale hardware/testbed appropriate to the domain (provided by department) | J7: MATLAB/Simulink, Python (Jupyter), LaTeX for documentation, Git, domain-specific EDA/ML tooling | K7: 6-12 months | L7: 4-6 (faculty-guided) | M7: High | N7: Medium | O7: High | P7: Medium | Q7: 3rd Year - PG | R7: 9
A8: P142 | B8: Edge AI | C8: Precision Agriculture Research Platform | D8: Faculty | E8: Faculty-Guided / Department Project | F8: A faculty-guided, department-scale on-device AI project that deploys a lightweight model to combine edge sensing and AI to optimize crop yield and resource use in real time. | G8: research methodology, systems integration, literature review & benchmarking, experimental design, technical documentation & reporting | H8: Domain-specific research stack (Python/MATLAB/Simulink + domain tools), version-controlled codebase | I8: Lab-scale hardware/testbed appropriate to the domain (provided by department) | J8: MATLAB/Simulink, Python (Jupyter), LaTeX for documentation, Git, domain-specific EDA/ML tooling | K8: 6-12 months | L8: 4-6 (faculty-guided) | M8: High | N8: Medium | O8: High | P8: Medium | Q8: 3rd Year - PG | R8: 8
A9: P143 | B9: VLSI | C9: Low-Power VLSI Design Research Lab Setup | D9: Faculty | E9: Faculty-Guided / Department Project | F9: A faculty-guided, department-scale digital-design project that involves build a reusable lab platform for evaluating low-power circuit techniques using hardware description languages. | G9: research methodology, systems integration, literature review & benchmarking, experimental design, technical documentation & reporting | H9: Domain-specific research stack (Python/MATLAB/Simulink + domain tools), version-controlled codebase | I9: Lab-scale hardware/testbed appropriate to the domain (provided by department) | J9: MATLAB/Simulink, Python (Jupyter), LaTeX for documentation, Git, domain-specific EDA/ML tooling | K9: 6-12 months | L9: 4-6 (faculty-guided) | M9: High | N9: Medium | O9: High | P9: Medium | Q9: 3rd Year - PG | R9: 9
A10: P144 | B10: Telecommunications | C10: 5G Testbed for Rural Connectivity Research | D10: Faculty | E10: Faculty-Guided / Department Project | F10: A faculty-guided, department-scale communication-systems project that evaluate 5G coverage and cost models for underserved rural regions. | G10: research methodology, systems integration, literature review & benchmarking, experimental design, technical documentation & reporting | H10: Domain-specific research stack (Python/MATLAB/Simulink + domain tools), version-controlled codebase | I10: Lab-scale hardware/testbed appropriate to the domain (provided by department) | J10: MATLAB/Simulink, Python (Jupyter), LaTeX for documentation, Git, domain-specific EDA/ML tooling | K10: 6-12 months | L10: 4-6 (faculty-guided) | M10: High | N10: Medium | O10: High | P10: Medium | Q10: 3rd Year - PG | R10: 8
A11: P145 | B11: AI/ML | C11: AI-Driven Disaster Management Platform | D11: Faculty | E11: Faculty-Guided / Department Project | F11: A faculty-guided, department-scale machine-learning project that trains and evaluates models to coordinate disaster response using predictive AI and real-time data feeds. | G11: research methodology, systems integration, literature review & benchmarking, experimental design, technical documentation & reporting | H11: Domain-specific research stack (Python/MATLAB/Simulink + domain tools), version-controlled codebase | I11: Lab-scale hardware/testbed appropriate to the domain (provided by department) | J11: MATLAB/Simulink, Python (Jupyter), LaTeX for documentation, Git, domain-specific EDA/ML tooling | K11: 6-12 months | L11: 4-6 (faculty-guided) | M11: High | N11: Medium | O11: High | P11: Medium | Q11: 3rd Year - PG | R11: 9
A12: P146 | B12: Embedded Systems | C12: Smart Waste Management Research System | D12: Faculty | E12: Faculty-Guided / Department Project | F12: A faculty-guided, department-scale hardware-software project that uses microcontrollers and sensors to optimize municipal waste collection routes using IoT fill-level sensors. | G12: research methodology, systems integration, literature review & benchmarking, experimental design, technical documentation & reporting | H12: Domain-specific research stack (Python/MATLAB/Simulink + domain tools), version-controlled codebase | I12: Lab-scale hardware/testbed appropriate to the domain (provided by department) | J12: MATLAB/Simulink, Python (Jupyter), LaTeX for documentation, Git, domain-specific EDA/ML tooling | K12: 6-12 months | L12: 4-6 (faculty-guided) | M12: High | N12: Medium | O12: High | P12: Medium | Q12: 3rd Year - PG | R12: 8
A13: P147 | B13: Embedded Systems | C13: Assistive Technology Platform for Differently-Abled Users | D13: Faculty | E13: Faculty-Guided / Department Project | F13: A faculty-guided, department-scale hardware-software project that uses microcontrollers and sensors to build sensor-assisted devices that improve accessibility and independence. | G13: research methodology, systems integration, literature review & benchmarking, experimental design, technical documentation & reporting | H13: Domain-specific research stack (Python/MATLAB/Simulink + domain tools), version-controlled codebase | I13: Lab-scale hardware/testbed appropriate to the domain (provided by department) | J13: MATLAB/Simulink, Python (Jupyter), LaTeX for documentation, Git, domain-specific EDA/ML tooling | K13: 6-12 months | L13: 4-6 (faculty-guided) | M13: High | N13: Medium | O13: High | P13: Medium | Q13: 3rd Year - PG | R13: 9
A14: P148 | B14: Management Systems | C14: Departmental Research Repository & Analytics Portal | D14: Faculty | E14: Faculty-Guided / Department Project | F14: A faculty-guided, department-scale web-based application that lets users centralize and analyze a department's publications, grants, and outputs through a structured, database-backed system. | G14: research methodology, systems integration, literature review & benchmarking, experimental design, technical documentation & reporting | H14: Domain-specific research stack (Python/MATLAB/Simulink + domain tools), version-controlled codebase | I14: Lab-scale hardware/testbed appropriate to the domain (provided by department) | J14: MATLAB/Simulink, Python (Jupyter), LaTeX for documentation, Git, domain-specific EDA/ML tooling | K14: 6-12 months | L14: 4-6 (faculty-guided) | M14: High | N14: Medium | O14: High | P14: Medium | Q14: 3rd Year - PG | R14: 8
... A24: P158 | B24: Edge AI | C24: Digital Twin Research Platform for Smart Manufacturing | D24: Faculty | E24: Faculty-Guided / Department Project | F24: A faculty-guided, department-scale on-device AI project that deploys a lightweight model to mirror a physical production line in a live, data-driven digital twin in real time. | G24: research methodology, systems integration, literature review & benchmarking, experimental design, technical documentation & reporting | H24: Domain-specific research stack (Python/MATLAB/Simulink + domain tools), version-controlled codebase | I24: Lab-scale hardware/testbed appropriate to the domain (provided by department) | J24: MATLAB/Simulink, Python (Jupyter), LaTeX for documentation, Git, domain-specific EDA/ML tooling | K24: 6-12 months | L24: 4-6 (faculty-guided) | M24: High | N24: Medium | O24: High | P24: Medium | Q24: 3rd Year - PG | R24: 8

Sheet Research Internship Projects
A1: Research Internship Projects — Engineering Project Roadmap
A2: Project ID | B2: Domain | C2: Project Name | D2: Difficulty Level | E2: Project Type | F2: Brief Description | G2: Key Concepts Learned | H2: Technologies Used | I2: Hardware Required | J2: Software Required | K2: Estimated Duration | L2: Team Size | M2: Resume Impact | N2: Placement Relevance | O2: Research Potential | P2: Startup Potential | Q2: Suitable Year | R2: Difficulty Score (1-10)
A3: P159 | B3: Edge AI | C3: TinyML Optimization for Ultra-Low-Power Devices | D3: Research | E3: Research Internship Project | F3: A research-oriented, publication-track on-device AI project that deploys a lightweight model to compress and optimize neural networks to run within microwatt power budgets in real time. | G3: novel algorithm/architecture design, experimental evaluation & benchmarking, statistical analysis of results, academic writing & publication preparation | H3: Domain-specific research/experimentation stack (Python/MATLAB/HDL as applicable), simulation & benchmarking tools | I3: Lab/simulation resources as required (GPU cluster, FPGA, SDR, or simulation-only, per project) | J3: Python/MATLAB, LaTeX, Git, domain-specific simulators (NS-3, Cadence, PyTorch, etc.) | K3: 6-12 months | L3: 1-2 (with mentor) | M3: High | N3: Medium | O3: High | P3: Low-Medium | Q3: Final Year / PG | R3: 10
A4: P160 | B4: VLSI | C4: RISC-V Accelerator Design for AI Workloads | D4: Research | E4: Research Internship Project | F4: A research-oriented, publication-track digital-design project that involves design a custom RISC-V extension/accelerator tuned for neural-network inference using hardware description languages. | G4: novel algorithm/architecture design, experimental evaluation & benchmarking, statistical analysis of results, academic writing & publication preparation | H4: Domain-specific research/experimentation stack (Python/MATLAB/HDL as applicable), simulation & benchmarking tools | I4: Lab/simulation resources as required (GPU cluster, FPGA, SDR, or simulation-only, per project) | J4: Python/MATLAB, LaTeX, Git, domain-specific simulators (NS-3, Cadence, PyTorch, etc.) | K4: 6-12 months | L4: 1-2 (with mentor) | M4: High | N4: Medium | O4: High | P4: Low-Medium | Q4: Final Year / PG | R4: 9
A5: P161 | B5: Edge AI | C5: Edge AI for Precision Agriculture | D5: Research | E5: Research Internship Project | F5: A research-oriented, publication-track on-device AI project that deploys a lightweight model to develop novel edge-inference techniques for crop and soil monitoring in real time. | G5: novel algorithm/architecture design, experimental evaluation & benchmarking, statistical analysis of results, academic writing & publication preparation | H5: Domain-specific research/experimentation stack (Python/MATLAB/HDL as applicable), simulation & benchmarking tools | I5: Lab/simulation resources as required (GPU cluster, FPGA, SDR, or simulation-only, per project) | J5: Python/MATLAB, LaTeX, Git, domain-specific simulators (NS-3, Cadence, PyTorch, etc.) | K5: 6-12 months | L5: 1-2 (with mentor) | M5: High | N5: Medium | O5: High | P5: Low-Medium | Q5: Final Year / PG | R5: 10
A6: P162 | B6: Telecommunications | C6: Telecom Network Optimization Using Reinforcement Learning | D6: Research | E6: Research Internship Project | F6: A research-oriented, publication-track communication-systems project that apply reinforcement learning to dynamically optimize network resource allocation. | G6: novel algorithm/architecture design, experimental evaluation & benchmarking, statistical analysis of results, academic writing & publication preparation | H6: Domain-specific research/experimentation stack (Python/MATLAB/HDL as applicable), simulation & benchmarking tools | I6: Lab/simulation resources as required (GPU cluster, FPGA, SDR, or simulation-only, per project) | J6: Python/MATLAB, LaTeX, Git, domain-specific simulators (NS-3, Cadence, PyTorch, etc.) | K6: 6-12 months | L6: 1-2 (with mentor) | M6: High | N6: Medium | O6: High | P6: Low-Medium | Q6: Final Year / PG | R6: 9
A7: P163 | B7: Telecommunications | C7: AI-Based Signal Processing for Radar Systems | D7: Research | E7: Research Internship Project | F7: A research-oriented, publication-track communication-systems project that apply deep learning techniques to improve radar target detection accuracy. | G7: novel algorithm/architecture design, experimental evaluation & benchmarking, statistical analysis of results, academic writing & publication preparation | H7: Domain-specific research/experimentation stack (Python/MATLAB/HDL as applicable), simulation & benchmarking tools | I7: Lab/simulation resources as required (GPU cluster, FPGA, SDR, or simulation-only, per project) | J7: Python/MATLAB, LaTeX, Git, domain-specific simulators (NS-3, Cadence, PyTorch, etc.) | K7: 6-12 months | L7: 1-2 (with mentor) | M7: High | N7: Medium | O7: High | P7: Low-Medium | Q7: Final Year / PG | R7: 10
A8: P164 | B8: VLSI | C8: Neuromorphic Computing Architecture Design | D8: Research | E8: Research Internship Project | F8: A research-oriented, publication-track digital-design project that involves design spiking-neural-network hardware inspired by biological computation using hardware description languages. | G8: novel algorithm/architecture design, experimental evaluation & benchmarking, statistical analysis of results, academic writing & publication preparation | H8: Domain-specific research/experimentation stack (Python/MATLAB/HDL as applicable), simulation & benchmarking tools | I8: Lab/simulation resources as required (GPU cluster, FPGA, SDR, or simulation-only, per project) | J8: Python/MATLAB, LaTeX, Git, domain-specific simulators (NS-3, Cadence, PyTorch, etc.) | K8: 6-12 months | L8: 1-2 (with mentor) | M8: High | N8: Medium | O8: High | P8: Low-Medium | Q8: Final Year / PG | R8: 9
A9: P165 | B9: AI/ML | C9: Federated Learning for Privacy-Preserving Healthcare AI | D9: Research | E9: Research Internship Project | F9: A research-oriented, publication-track machine-learning project that trains and evaluates models to develop privacy-preserving federated training methods for clinical models. | G9: novel algorithm/architecture design, experimental evaluation & benchmarking, statistical analysis of results, academic writing & publication preparation | H9: Domain-specific research/experimentation stack (Python/MATLAB/HDL as applicable), simulation & benchmarking tools | I9: Lab/simulation resources as required (GPU cluster, FPGA, SDR, or simulation-only, per project) | J9: Python/MATLAB, LaTeX, Git, domain-specific simulators (NS-3, Cadence, PyTorch, etc.) | K9: 6-12 months | L9: 1-2 (with mentor) | M9: High | N9: Medium | O9: High | P9: Low-Medium | Q9: Final Year / PG | R9: 10
A10: P166 | B10: VLSI | C10: Low-Power VLSI Design for Biomedical Implants | D10: Research | E10: Research Internship Project | F10: A research-oriented, publication-track digital-design project that involves design ultra-low-power circuits suitable for implantable medical devices using hardware description languages. | G10: novel algorithm/architecture design, experimental evaluation & benchmarking, statistical analysis of results, academic writing & publication preparation | H10: Domain-specific research/experimentation stack (Python/MATLAB/HDL as applicable), simulation & benchmarking tools | I10: Lab/simulation resources as required (GPU cluster, FPGA, SDR, or simulation-only, per project) | J10: Python/MATLAB, LaTeX, Git, domain-specific simulators (NS-3, Cadence, PyTorch, etc.) | K10: 6-12 months | L10: 1-2 (with mentor) | M10: High | N10: Medium | O10: High | P10: Low-Medium | Q10: Final Year / PG | R10: 9
A11: P167 | B11: AI/ML | C11: Explainable AI for Medical Diagnosis | D11: Research | E11: Research Internship Project | F11: A research-oriented, publication-track machine-learning project that trains and evaluates models to develop interpretable AI models that clinicians can trust for diagnosis support. | G11: novel algorithm/architecture design, experimental evaluation & benchmarking, statistical analysis of results, academic writing & publication preparation | H11: Domain-specific research/experimentation stack (Python/MATLAB/HDL as applicable), simulation & benchmarking tools | I11: Lab/simulation resources as required (GPU cluster, FPGA, SDR, or simulation-only, per project) | J11: Python/MATLAB, LaTeX, Git, domain-specific simulators (NS-3, Cadence, PyTorch, etc.) | K11: 6-12 months | L11: 1-2 (with mentor) | M11: High | N11: Medium | O11: High | P11: Low-Medium | Q11: Final Year / PG | R11: 10
A12: P168 | B12: Telecommunications | C12: 6G Waveform Design and Simulation | D12: Research | E12: Research Internship Project | F12: A research-oriented, publication-track communication-systems project that design and simulate candidate waveforms for next-generation 6G networks. | G12: novel algorithm/architecture design, experimental evaluation & benchmarking, statistical analysis of results, academic writing & publication preparation | H12: Domain-specific research/experimentation stack (Python/MATLAB/HDL as applicable), simulation & benchmarking tools | I12: Lab/simulation resources as required (GPU cluster, FPGA, SDR, or simulation-only, per project) | J12: Python/MATLAB, LaTeX, Git, domain-specific simulators (NS-3, Cadence, PyTorch, etc.) | K12: 6-12 months | L12: 1-2 (with mentor) | M12: High | N12: Medium | O12: High | P12: Low-Medium | Q12: Final Year / PG | R12: 9
A13: P169 | B13: AI/ML | C13: Quantum Machine Learning Algorithms | D13: Research | E13: Research Internship Project | F13: A research-oriented, publication-track machine-learning project that trains and evaluates models to explore quantum-computing approaches to accelerate machine-learning algorithms. | G13: novel algorithm/architecture design, experimental evaluation & benchmarking, statistical analysis of results, academic writing & publication preparation | H13: Domain-specific research/experimentation stack (Python/MATLAB/HDL as applicable), simulation & benchmarking tools | I13: Lab/simulation resources as required (GPU cluster, FPGA, SDR, or simulation-only, per project) | J13: Python/MATLAB, LaTeX, Git, domain-specific simulators (NS-3, Cadence, PyTorch, etc.) | K13: 6-12 months | L13: 1-2 (with mentor) | M13: High | N13: Medium | O13: High | P13: Low-Medium | Q13: Final Year / PG | R13: 10
A14: P170 | B14: VLSI | C14: Approximate Computing for Energy-Efficient AI Accelerators | D14: Research | E14: Research Internship Project | F14: A research-oriented, publication-track digital-design project that involves trade off numerical precision for energy savings in AI accelerator hardware using hardware description languages. | G14: novel algorithm/architecture design, experimental evaluation & benchmarking, statistical analysis of results, academic writing & publication preparation | H14: Domain-specific research/experimentation stack (Python/MATLAB/HDL as applicable), simulation & benchmarking tools | I14: Lab/simulation resources as required (GPU cluster, FPGA, SDR, or simulation-only, per project) | J14: Python/MATLAB, LaTeX, Git, domain-specific simulators (NS-3, Cadence, PyTorch, etc.) | K14: 6-12 months | L14: 1-2 (with mentor) | M14: High | N14: Medium | O14: High | P14: Low-Medium | Q14: Final Year / PG | R14: 9
... A24: P180 | B24: AI/ML | C24: Reinforcement Learning for Autonomous Robotic Manipulation | D24: Research | E24: Research Internship Project | F24: A research-oriented, publication-track machine-learning project that trains and evaluates models to train RL policies that let a robotic arm learn dexterous manipulation tasks. | G24: novel algorithm/architecture design, experimental evaluation & benchmarking, statistical analysis of results, academic writing & publication preparation | H24: Domain-specific research/experimentation stack (Python/MATLAB/HDL as applicable), simulation & benchmarking tools | I24: Lab/simulation resources as required (GPU cluster, FPGA, SDR, or simulation-only, per project) | J24: Python/MATLAB, LaTeX, Git, domain-specific simulators (NS-3, Cadence, PyTorch, etc.) | K24: 6-12 months | L24: 1-2 (with mentor) | M24: High | N24: Medium | O24: High | P24: Low-Medium | Q24: Final Year / PG | R24: 9
